backtrader_mootdx/__init__.py
backtrader_mootdx/backtrader_mootdx.py
backtrader_mootdx-0.1.0.dist-info/LICENSE
backtrader_mootdx-0.1.0.dist-info/METADATA
backtrader_mootdx-0.1.0.dist-info/WHEEL
backtrader_mootdx-0.1.0.dist-info/top_level.txt
backtrader_mootdx-0.1.0.dist-info/RECORD
